isotope/__init__.py
isotope/_optional.py
isotope/cli.py
isotope/ingestor.py
isotope/isotope.py
isotope/py.typed
isotope/retriever.py
isotope/settings.py
isotope/atomizer/__init__.py
isotope/atomizer/base.py
isotope/atomizer/llm.py
isotope/atomizer/sentence.py
isotope/configuration/__init__.py
isotope/configuration/base.py
isotope/configuration/providers/__init__.py
isotope/configuration/providers/litellm.py
isotope/configuration/storage/__init__.py
isotope/configuration/storage/local.py
isotope/embedder/__init__.py
isotope/embedder/base.py
isotope/embedder/client.py
isotope/loaders/__init__.py
isotope/loaders/base.py
isotope/loaders/html.py
isotope/loaders/pdfplumber_loader.py
isotope/loaders/pypdf_loader.py
isotope/loaders/registry.py
isotope/loaders/text.py
isotope/models/__init__.py
isotope/models/atom.py
isotope/models/chunk.py
isotope/models/question.py
isotope/models/results.py
isotope/providers/__init__.py
isotope/providers/base.py
isotope/providers/litellm/__init__.py
isotope/providers/litellm/client.py
isotope/providers/litellm/models.py
isotope/question_generator/__init__.py
isotope/question_generator/base.py
isotope/question_generator/client.py
isotope/question_generator/diversity_filter.py
isotope/question_generator/exceptions.py
isotope/stores/__init__.py
isotope/stores/base.py
isotope/stores/chroma.py
isotope/stores/source_registry.py
isotope/stores/sqlite_atom.py
isotope/stores/sqlite_chunk.py
isotope_rag-0.1.0.dist-info/METADATA
isotope_rag-0.1.0.dist-info/WHEEL
isotope_rag-0.1.0.dist-info/entry_points.txt
isotope_rag-0.1.0.dist-info/licenses/LICENSE
isotope_rag-0.1.0.dist-info/RECORD
