Metadata-Version: 2.4
Name: isotope-rag
Version: 0.1.0
Summary: Reverse RAG database - index questions, not chunks
Project-URL: Repository, https://github.com/sreejithraman/isotope
Project-URL: Documentation, https://github.com/sreejithraman/isotope#readme
Author: Sree Raman
License-Expression: MIT
License-File: LICENSE
Keywords: document-processing,embeddings,question-generation,rag,vector-database
Classifier: Development Status :: 3 - Alpha
Classifier: Intended Audience :: Developers
Classifier: License :: OSI Approved :: MIT License
Classifier: Programming Language :: Python :: 3.11
Classifier: Programming Language :: Python :: 3.12
Requires-Python: >=3.11
Requires-Dist: numpy<3,>=1.24
Requires-Dist: pydantic<3,>=2.0
Requires-Dist: pysbd<1,>=0.3.4
Provides-Extra: all
Requires-Dist: beautifulsoup4>=4.12; extra == 'all'
Requires-Dist: chromadb>=0.4; extra == 'all'
Requires-Dist: litellm>=1.0; extra == 'all'
Requires-Dist: markdownify>=0.13; extra == 'all'
Requires-Dist: pdfplumber>=0.11; extra == 'all'
Requires-Dist: pyyaml>=6.0; extra == 'all'
Requires-Dist: rich>=13.0; extra == 'all'
Requires-Dist: typer>=0.9; extra == 'all'
Provides-Extra: chroma
Requires-Dist: chromadb>=0.4; extra == 'chroma'
Provides-Extra: cli
Requires-Dist: pyyaml>=6.0; extra == 'cli'
Requires-Dist: rich>=13.0; extra == 'cli'
Requires-Dist: typer>=0.9; extra == 'cli'
Provides-Extra: dev
Requires-Dist: build>=1.0; extra == 'dev'
Requires-Dist: litellm>=1.0; extra == 'dev'
Requires-Dist: mypy>=1.10; extra == 'dev'
Requires-Dist: pre-commit>=3.7; extra == 'dev'
Requires-Dist: pytest-asyncio>=0.23; extra == 'dev'
Requires-Dist: pytest>=8.0; extra == 'dev'
Requires-Dist: ruff>=0.14; extra == 'dev'
Provides-Extra: html
Requires-Dist: beautifulsoup4>=4.12; extra == 'html'
Requires-Dist: markdownify>=0.13; extra == 'html'
Provides-Extra: litellm
Requires-Dist: litellm>=1.0; extra == 'litellm'
Provides-Extra: loaders
Requires-Dist: beautifulsoup4>=4.12; extra == 'loaders'
Requires-Dist: markdownify>=0.13; extra == 'loaders'
Requires-Dist: pdfplumber>=0.11; extra == 'loaders'
Provides-Extra: pdf
Requires-Dist: pdfplumber>=0.11; extra == 'pdf'
Provides-Extra: pdf-text
Requires-Dist: pypdf>=4.0; extra == 'pdf-text'
